pytest_qatouch/__init__.py
pytest_qatouch/plugin.py
pytest_qatouch/qatouch.py
pytest_qatouch/utils.py
pytest_qatouch-0.2.2.dist-info/LICENSE
pytest_qatouch-0.2.2.dist-info/METADATA
pytest_qatouch-0.2.2.dist-info/WHEEL
pytest_qatouch-0.2.2.dist-info/entry_points.txt
pytest_qatouch-0.2.2.dist-info/top_level.txt
pytest_qatouch-0.2.2.dist-info/RECORD
