Metadata-Version: 2.1
Name: pytest-qatouch
Version: 0.2.2
Summary: Pytest plugin for uploading test results to your QA Touch Testrun.
Home-page: https://github.com/MohamedRaslan/pytest-qatouch
Author: Mohamed Raslan
Author-email: MohamedRaslanG@gmail.com
License: MIT License
Project-URL: Source, https://github.com/MohamedRaslan/pytest-qatouch
Project-URL: Tracker, https://github.com/MohamedRaslan/pytest-qatouch/issues
Keywords: qatouch,pytest,pytest-qatouch,pytest-pyqatouch
Classifier: Development Status :: 4 - Beta
Classifier: Framework :: Pytest
Classifier: Environment :: Plugins
Classifier: Operating System :: OS Independent
Classifier: Intended Audience :: Developers
Classifier: Programming Language :: Python
Classifier: Programming Language :: Python :: 3
Classifier: Programming Language :: Python :: 3.7
Classifier: Programming Language :: Python :: 3.8
Classifier: Programming Language :: Python :: 3.9
Classifier: Programming Language :: Python :: 3 :: Only
Classifier: Programming Language :: Python :: Implementation :: CPython
Classifier: Programming Language :: Python :: Implementation :: PyPy
Classifier: Topic :: Software Development :: Testing
Classifier: Topic :: Software Development :: Quality Assurance
Classifier: License :: OSI Approved :: MIT License
Requires-Python: >=3.7
License-File: LICENSE
Requires-Dist: pytest (>=6.2.0)
Requires-Dist: requests (>=2.25.1)
Provides-Extra: dev
Requires-Dist: bump2version (>=1.0.1) ; extra == 'dev'
Requires-Dist: pytest-cov (>=2.12.1) ; extra == 'dev'
Requires-Dist: responses (>=0.13.3) ; extra == 'dev'
